<?xml version="1.0" ?>
<routes>
 <trip id="v-0" from="F6G6" to="F3F4" depart="0"/>
 <trip id="v-1" from="I7H7" to="I2H2" depart="1"/>
 <trip id="v-2" from="C5D5" to="H6G6" depart="2"/>
 <trip id="v-3" from="E1E0" to="B7C7" depart="3"/>
 <trip id="v-4" from="G0F0" to="G7F7" depart="4"/>
 <trip id="v-5" from="C2D2" to="F6F5" depart="5"/>
 <trip id="v-6" from="C7C6" to="H2G2" depart="6"/>
 <trip id="v-7" from="H6I6" to="C8C7" depart="7"/>
 <trip id="v-8" from="D1D0" to="C8D8" depart="8"/>
 <trip id="v-9" from="D7D8" to="G2H2" depart="9"/>
 <trip id="v-10" from="I4J4" to="E5D5" depart="10"/>
 <trip id="v-11" from="B4A4" to="F3G3" depart="11"/>
 <trip id="v-12" from="H5I5" to="D9E9" depart="12"/>
 <trip id="v-13" from="D0C0" to="J6I6" depart="13"/>
 <trip id="v-14" from="D5E5" to="H7G7" depart="14"/>
 <trip id="v-15" from="H0H1" to="I6J6" depart="15"/>
 <trip id="v-16" from="B7A7" to="G7H7" depart="16"/>
 <trip id="v-17" from="A6B6" to="B0C0" depart="17"/>
 <trip id="v-18" from="I1J1" to="B8B7" depart="18"/>
 <trip id="v-19" from="D7D8" to="I5I6" depart="19"/>
 <trip id="v-20" from="C3D3" to="C7B7" depart="20"/>
 <trip id="v-21" from="E1E2" to="C7B7" depart="21"/>
 <trip id="v-22" from="A9B9" to="A4B4" depart="22"/>
 <trip id="v-23" from="B7B8" to="J9J8" depart="23"/>
 <trip id="v-24" from="A7A8" to="G8F8" depart="24"/>
 <trip id="v-25" from="B4A4" to="B9B8" depart="25"/>
 <trip id="v-26" from="I0J0" to="A0B0" depart="26"/>
 <trip id="v-27" from="J3I3" to="D6D5" depart="27"/>
 <trip id="v-28" from="H2H3" to="E3E4" depart="28"/>
 <trip id="v-29" from="E8D8" to="I5H5" depart="29"/>
 <trip id="v-30" from="E6E5" to="G8H8" depart="30"/>
 <trip id="v-31" from="A0B0" to="H0H1" depart="31"/>
 <trip id="v-32" from="E5D5" to="G0F0" depart="32"/>
 <trip id="v-33" from="J3I3" to="B6A6" depart="33"/>
 <trip id="v-34" from="E9E8" to="I9H9" depart="34"/>
 <trip id="v-35" from="D2D1" to="I9J9" depart="35"/>
 <trip id="v-36" from="G8H8" to="B9C9" depart="36"/>
 <trip id="v-37" from="A0B0" to="E8E7" depart="37"/>
 <trip id="v-38" from="C9D9" to="G1H1" depart="38"/>
 <trip id="v-39" from="I1J1" to="B1A1" depart="39"/>
 <trip id="v-40" from="D5C5" to="A1A0" depart="40"/>
 <trip id="v-41" from="I4I3" to="C6B6" depart="41"/>
 <trip id="v-42" from="E5E6" to="G4G3" depart="42"/>
 <trip id="v-43" from="C9D9" to="J6I6" depart="43"/>
 <trip id="v-44" from="D6E6" to="F3F2" depart="44"/>
 <trip id="v-45" from="E1E2" to="H1G1" depart="45"/>
 <trip id="v-46" from="E8E7" to="J2I2" depart="46"/>
 <trip id="v-47" from="G4G3" to="E4D4" depart="47"/>
 <trip id="v-48" from="I2I3" to="G5F5" depart="48"/>
 <trip id="v-49" from="I8I7" to="J0J1" depart="49"/>
 <trip id="v-50" from="G4F4" to="D6C6" depart="50"/>
 <trip id="v-51" from="F5G5" to="B3B4" depart="51"/>
 <trip id="v-52" from="E6D6" to="I0J0" depart="52"/>
 <trip id="v-53" from="A5B5" to="G1H1" depart="53"/>
 <trip id="v-54" from="H5I5" to="H2H1" depart="54"/>
 <trip id="v-55" from="H5I5" to="C1B1" depart="55"/>
 <trip id="v-56" from="D7C7" to="I6J6" depart="56"/>
 <trip id="v-57" from="I5H5" to="H3G3" depart="57"/>
 <trip id="v-58" from="H8H7" to="B4B3" depart="58"/>
 <trip id="v-59" from="B4A4" to="G2G3" depart="59"/>
 <trip id="v-60" from="D9E9" to="H9G9" depart="60"/>
 <trip id="v-61" from="F5F6" to="E8D8" depart="61"/>
 <trip id="v-62" from="G4F4" to="G5F5" depart="62"/>
 <trip id="v-63" from="B2C2" to="B6B7" depart="63"/>
 <trip id="v-64" from="A1B1" to="H3I3" depart="64"/>
 <trip id="v-65" from="B1A1" to="F9F8" depart="65"/>
 <trip id="v-66" from="G8F8" to="G3F3" depart="66"/>
 <trip id="v-67" from="I8J8" to="C6B6" depart="67"/>
 <trip id="v-68" from="I9J9" to="J4J3" depart="68"/>
 <trip id="v-69" from="I3I2" to="E7E8" depart="69"/>
 <trip id="v-70" from="H8G8" to="D2D1" depart="70"/>
 <trip id="v-71" from="D8C8" to="F6F5" depart="71"/>
 <trip id="v-72" from="J7J8" to="I3H3" depart="72"/>
 <trip id="v-73" from="C7C6" to="G6G7" depart="73"/>
 <trip id="v-74" from="D0C0" to="D7D6" depart="74"/>
 <trip id="v-75" from="A0B0" to="I7I6" depart="75"/>
 <trip id="v-76" from="B2A2" to="E8E9" depart="76"/>
 <trip id="v-77" from="E7E8" to="I4I3" depart="77"/>
 <trip id="v-78" from="B8C8" to="D0D1" depart="78"/>
 <trip id="v-79" from="J9I9" to="J3I3" depart="79"/>
 <trip id="v-80" from="J5J6" to="A6A5" depart="80"/>
 <trip id="v-81" from="F8G8" to="C3C2" depart="81"/>
 <trip id="v-82" from="E1E2" to="C7B7" depart="82"/>
 <trip id="v-83" from="H0H1" to="C5B5" depart="83"/>
 <trip id="v-84" from="G8H8" to="D5D6" depart="84"/>
 <trip id="v-85" from="F2G2" to="J6J5" depart="85"/>
 <trip id="v-86" from="C9B9" to="F8F7" depart="86"/>
 <trip id="v-87" from="F1F0" to="H8I8" depart="87"/>
 <trip id="v-88" from="I9H9" to="B6B7" depart="88"/>
 <trip id="v-89" from="D8C8" to="G8G9" depart="89"/>
 <trip id="v-90" from="F6F7" to="B2C2" depart="90"/>
 <trip id="v-91" from="F9G9" to="C6C5" depart="91"/>
 <trip id="v-92" from="G9G8" to="H1I1" depart="92"/>
 <trip id="v-93" from="A4B4" to="J8J9" depart="93"/>
 <trip id="v-94" from="B8B9" to="A4A3" depart="94"/>
 <trip id="v-95" from="C3C2" to="F3F4" depart="95"/>
 <trip id="v-96" from="A5A6" to="C0B0" depart="96"/>
 <trip id="v-97" from="B5A5" to="H3I3" depart="97"/>
 <trip id="v-98" from="A7A8" to="F3F2" depart="98"/>
 <trip id="v-99" from="C8B8" to="G0F0" depart="99"/>
 <trip id="v-100" from="F0F1" to="E2E1" depart="100"/>
 <trip id="v-101" from="A1B1" to="G1G2" depart="101"/>
 <trip id="v-102" from="A9A8" to="F6F7" depart="102"/>
 <trip id="v-103" from="D6C6" to="I6H6" depart="103"/>
 <trip id="v-104" from="B4C4" to="H7H6" depart="104"/>
 <trip id="v-105" from="F9G9" to="B2C2" depart="105"/>
 <trip id="v-106" from="G6G5" to="J0J1" depart="106"/>
 <trip id="v-107" from="I2I3" to="D7D6" depart="107"/>
 <trip id="v-108" from="A8A9" to="H0H1" depart="108"/>
 <trip id="v-109" from="B1A1" to="J6J5" depart="109"/>
 <trip id="v-110" from="H0I0" to="J8I8" depart="110"/>
 <trip id="v-111" from="E8E9" to="J0J1" depart="111"/>
 <trip id="v-112" from="J2J3" to="B6B5" depart="112"/>
 <trip id="v-113" from="I9J9" to="J3I3" depart="113"/>
 <trip id="v-114" from="C2C3" to="E6E5" depart="114"/>
 <trip id="v-115" from="H9H8" to="G3F3" depart="115"/>
 <trip id="v-116" from="D0D1" to="F1F0" depart="116"/>
 <trip id="v-117" from="A0B0" to="J9I9" depart="117"/>
 <trip id="v-118" from="E0E1" to="G7H7" depart="118"/>
 <trip id="v-119" from="I7I6" to="E8E9" depart="119"/>
 <trip id="v-120" from="I5H5" to="G3G4" depart="120"/>
 <trip id="v-121" from="A0B0" to="G0H0" depart="121"/>
 <trip id="v-122" from="H7G7" to="I2I3" depart="122"/>
 <trip id="v-123" from="A7A6" to="D1E1" depart="123"/>
 <trip id="v-124" from="J1J0" to="H5H6" depart="124"/>
 <trip id="v-125" from="H0G0" to="G6H6" depart="125"/>
 <trip id="v-126" from="E9E8" to="A3A4" depart="126"/>
 <trip id="v-127" from="B8A8" to="I8J8" depart="127"/>
 <trip id="v-128" from="E9E8" to="F5F6" depart="128"/>
 <trip id="v-129" from="C2C1" to="F5F6" depart="129"/>
 <trip id="v-130" from="E5D5" to="C3C4" depart="130"/>
 <trip id="v-131" from="B0B1" to="G2H2" depart="131"/>
 <trip id="v-132" from="F0F1" to="D5C5" depart="132"/>
 <trip id="v-133" from="B5C5" to="G6F6" depart="133"/>
 <trip id="v-134" from="B4A4" to="D9C9" depart="134"/>
 <trip id="v-135" from="E2E3" to="H7H6" depart="135"/>
 <trip id="v-136" from="A6B6" to="I0J0" depart="136"/>
 <trip id="v-137" from="E7E8" to="C0B0" depart="137"/>
 <trip id="v-138" from="J3J4" to="C5D5" depart="138"/>
 <trip id="v-139" from="C7C8" to="I8I9" depart="139"/>
 <trip id="v-140" from="H7G7" to="A5A6" depart="140"/>
 <trip id="v-141" from="D9E9" to="J6J7" depart="141"/>
 <trip id="v-142" from="E8D8" to="I4J4" depart="142"/>
 <trip id="v-143" from="E0D0" to="F4F3" depart="143"/>
 <trip id="v-144" from="A9A8" to="G4G3" depart="144"/>
 <trip id="v-145" from="J3J4" to="D6C6" depart="145"/>
 <trip id="v-146" from="J4J3" to="B1B2" depart="146"/>
 <trip id="v-147" from="F4F3" to="D5C5" depart="147"/>
 <trip id="v-148" from="J6J5" to="A6A5" depart="148"/>
 <trip id="v-149" from="J2I2" to="G5G6" depart="149"/>
 <trip id="v-150" from="J5J6" to="F2F1" depart="150"/>
 <trip id="v-151" from="C1C0" to="F6F5" depart="151"/>
 <trip id="v-152" from="G5G6" to="E6D6" depart="152"/>
 <trip id="v-153" from="G1G0" to="D5E5" depart="153"/>
 <trip id="v-154" from="G6G7" to="D0D1" depart="154"/>
 <trip id="v-155" from="C3C4" to="F7F6" depart="155"/>
 <trip id="v-156" from="H2I2" to="D6D7" depart="156"/>
 <trip id="v-157" from="J8J9" to="J1I1" depart="157"/>
 <trip id="v-158" from="D3C3" to="F9G9" depart="158"/>
 <trip id="v-159" from="J0J1" to="H5I5" depart="159"/>
 <trip id="v-160" from="F2G2" to="B5B6" depart="160"/>
 <trip id="v-161" from="D0D1" to="H2H1" depart="161"/>
 <trip id="v-162" from="I2I1" to="E6E7" depart="162"/>
 <trip id="v-163" from="I5H5" to="E4E3" depart="163"/>
 <trip id="v-164" from="B5C5" to="C0C1" depart="164"/>
 <trip id="v-165" from="F9G9" to="C5D5" depart="165"/>
 <trip id="v-166" from="I8H8" to="C1D1" depart="166"/>
 <trip id="v-167" from="G0F0" to="I5H5" depart="167"/>
 <trip id="v-168" from="J2I2" to="D3D2" depart="168"/>
 <trip id="v-169" from="A2A1" to="J1J2" depart="169"/>
 <trip id="v-170" from="D2D3" to="F7F8" depart="170"/>
 <trip id="v-171" from="E8E7" to="F7G7" depart="171"/>
 <trip id="v-172" from="J1J2" to="G5H5" depart="172"/>
 <trip id="v-173" from="J7J6" to="D2C2" depart="173"/>
 <trip id="v-174" from="B8B9" to="H5G5" depart="174"/>
 <trip id="v-175" from="D4D3" to="H9H8" depart="175"/>
 <trip id="v-176" from="H3H4" to="C4B4" depart="176"/>
 <trip id="v-177" from="G2H2" to="G5F5" depart="177"/>
 <trip id="v-178" from="I8I7" to="E4E3" depart="178"/>
 <trip id="v-179" from="A2A1" to="J4I4" depart="179"/>
 <trip id="v-180" from="F6G6" to="H0I0" depart="180"/>
 <trip id="v-181" from="F4F3" to="B8B9" depart="181"/>
 <trip id="v-182" from="C2B2" to="F0G0" depart="182"/>
 <trip id="v-183" from="G4F4" to="D4C4" depart="183"/>
 <trip id="v-184" from="A2A1" to="G6F6" depart="184"/>
 <trip id="v-185" from="C4C3" to="A9B9" depart="185"/>
 <trip id="v-186" from="A8A9" to="G2G3" depart="186"/>
 <trip id="v-187" from="B5A5" to="A3A4" depart="187"/>
 <trip id="v-188" from="E2E1" to="F0G0" depart="188"/>
 <trip id="v-189" from="D5D6" to="G2H2" depart="189"/>
 <trip id="v-190" from="H7H8" to="D3D2" depart="190"/>
 <trip id="v-191" from="A6A7" to="I6J6" depart="191"/>
 <trip id="v-192" from="H5I5" to="C9B9" depart="192"/>
 <trip id="v-193" from="F4G4" to="G6G5" depart="193"/>
 <trip id="v-194" from="H1H0" to="E0D0" depart="194"/>
 <trip id="v-195" from="F0G0" to="A3A4" depart="195"/>
 <trip id="v-196" from="H4H3" to="C3D3" depart="196"/>
 <trip id="v-197" from="D9D8" to="G0G1" depart="197"/>
 <trip id="v-198" from="J3J2" to="B5A5" depart="198"/>
 <trip id="v-199" from="H9I9" to="C3C4" depart="199"/>
 <trip id="v-200" from="I2I3" to="B8B9" depart="200"/>
 <trip id="v-201" from="H0I0" to="E1D1" depart="201"/>
 <trip id="v-202" from="F3F2" to="I5I6" depart="202"/>
 <trip id="v-203" from="B1A1" to="C5B5" depart="203"/>
 <trip id="v-204" from="B9C9" to="H7I7" depart="204"/>
 <trip id="v-205" from="A8A7" to="I7I6" depart="205"/>
 <trip id="v-206" from="C7C6" to="G3G4" depart="206"/>
 <trip id="v-207" from="F7F6" to="A2A3" depart="207"/>
 <trip id="v-208" from="J3J2" to="E0E1" depart="208"/>
 <trip id="v-209" from="J3I3" to="C2D2" depart="209"/>
 <trip id="v-210" from="D8C8" to="A4B4" depart="210"/>
 <trip id="v-211" from="F3F4" to="C2C1" depart="211"/>
 <trip id="v-212" from="A7A8" to="G4F4" depart="212"/>
 <trip id="v-213" from="H9G9" to="C0B0" depart="213"/>
 <trip id="v-214" from="H5G5" to="H2H1" depart="214"/>
 <trip id="v-215" from="A4B4" to="G2G3" depart="215"/>
 <trip id="v-216" from="H0I0" to="D6D7" depart="216"/>
 <trip id="v-217" from="J9I9" to="E0D0" depart="217"/>
 <trip id="v-218" from="A6A7" to="F9F8" depart="218"/>
 <trip id="v-219" from="D4E4" to="J3J4" depart="219"/>
 <trip id="v-220" from="A1B1" to="J0I0" depart="220"/>
 <trip id="v-221" from="J7J8" to="A7A6" depart="221"/>
 <trip id="v-222" from="D7D8" to="A0B0" depart="222"/>
 <trip id="v-223" from="C8D8" to="A0B0" depart="223"/>
 <trip id="v-224" from="E5E6" to="G5H5" depart="224"/>
 <trip id="v-225" from="C6C5" to="J2J1" depart="225"/>
 <trip id="v-226" from="H4H3" to="D1D0" depart="226"/>
 <trip id="v-227" from="B3B2" to="A9B9" depart="227"/>
 <trip id="v-228" from="A0A1" to="I6I5" depart="228"/>
 <trip id="v-229" from="C8C7" to="F9G9" depart="229"/>
 <trip id="v-230" from="C0C1" to="I7I6" depart="230"/>
 <trip id="v-231" from="G1H1" to="E3E4" depart="231"/>
 <trip id="v-232" from="B9C9" to="I3I4" depart="232"/>
 <trip id="v-233" from="B5B6" to="I6I7" depart="233"/>
 <trip id="v-234" from="B7B8" to="F8G8" depart="234"/>
 <trip id="v-235" from="A1A0" to="D9D8" depart="235"/>
 <trip id="v-236" from="H0H1" to="C7C6" depart="236"/>
 <trip id="v-237" from="J8J9" to="E8E9" depart="237"/>
 <trip id="v-238" from="D3D2" to="D6D5" depart="238"/>
 <trip id="v-239" from="J8J9" to="A2B2" depart="239"/>
 <trip id="v-240" from="A9B9" to="G0H0" depart="240"/>
 <trip id="v-241" from="J9J8" to="B6B5" depart="241"/>
 <trip id="v-242" from="C7D7" to="H9G9" depart="242"/>
 <trip id="v-243" from="C3C4" to="B8C8" depart="243"/>
 <trip id="v-244" from="F3F4" to="C9D9" depart="244"/>
 <trip id="v-245" from="A4A3" to="G8G7" depart="245"/>
 <trip id="v-246" from="B5C5" to="I9J9" depart="246"/>
 <trip id="v-247" from="G6F6" to="A1A0" depart="247"/>
 <trip id="v-248" from="C2C3" to="B8B7" depart="248"/>
 <trip id="v-249" from="I2H2" to="F6F5" depart="249"/>
 <trip id="v-250" from="H3I3" to="D7C7" depart="250"/>
 <trip id="v-251" from="G1G0" to="B2A2" depart="251"/>
 <trip id="v-252" from="H4H3" to="F8G8" depart="252"/>
 <trip id="v-253" from="E6E7" to="F5G5" depart="253"/>
 <trip id="v-254" from="F2G2" to="C5D5" depart="254"/>
 <trip id="v-255" from="G5H5" to="D9E9" depart="255"/>
 <trip id="v-256" from="A1A2" to="J9I9" depart="256"/>
 <trip id="v-257" from="I0J0" to="B0C0" depart="257"/>
 <trip id="v-258" from="A8B8" to="F9G9" depart="258"/>
 <trip id="v-259" from="E9E8" to="G2H2" depart="259"/>
 <trip id="v-260" from="B2A2" to="B9C9" depart="260"/>
 <trip id="v-261" from="B3B4" to="J5I5" depart="261"/>
 <trip id="v-262" from="J7I7" to="F3G3" depart="262"/>
 <trip id="v-263" from="J9I9" to="A8B8" depart="263"/>
 <trip id="v-264" from="G2G1" to="B9B8" depart="264"/>
 <trip id="v-265" from="J8J7" to="F1F2" depart="265"/>
 <trip id="v-266" from="D9D8" to="H4G4" depart="266"/>
 <trip id="v-267" from="I4I3" to="F7F8" depart="267"/>
 <trip id="v-268" from="F4G4" to="D3D2" depart="268"/>
 <trip id="v-269" from="F6G6" to="H3H2" depart="269"/>
 <trip id="v-270" from="H8I8" to="E6E5" depart="270"/>
 <trip id="v-271" from="C8D8" to="B2B3" depart="271"/>
 <trip id="v-272" from="A6A7" to="D1C1" depart="272"/>
 <trip id="v-273" from="I3I4" to="J6I6" depart="273"/>
 <trip id="v-274" from="G1H1" to="F9G9" depart="274"/>
 <trip id="v-275" from="G9F9" to="G4F4" depart="275"/>
 <trip id="v-276" from="I4H4" to="C4B4" depart="276"/>
 <trip id="v-277" from="H2H3" to="B0C0" depart="277"/>
 <trip id="v-278" from="E7D7" to="B3A3" depart="278"/>
 <trip id="v-279" from="B5A5" to="F8G8" depart="279"/>
 <trip id="v-280" from="E6E7" to="J5I5" depart="280"/>
 <trip id="v-281" from="J8I8" to="D3C3" depart="281"/>
 <trip id="v-282" from="H2I2" to="J6J5" depart="282"/>
 <trip id="v-283" from="J0J1" to="A2A3" depart="283"/>
 <trip id="v-284" from="I0J0" to="I6I5" depart="284"/>
 <trip id="v-285" from="I4J4" to="C3C2" depart="285"/>
 <trip id="v-286" from="F3G3" to="D4D3" depart="286"/>
 <trip id="v-287" from="A2A3" to="H6G6" depart="287"/>
 <trip id="v-288" from="J5I5" to="E1D1" depart="288"/>
 <trip id="v-289" from="D2D3" to="I3I4" depart="289"/>
 <trip id="v-290" from="B9C9" to="H3H4" depart="290"/>
 <trip id="v-291" from="D9D8" to="D1E1" depart="291"/>
 <trip id="v-292" from="E9D9" to="J1I1" depart="292"/>
 <trip id="v-293" from="A9A8" to="A4A3" depart="293"/>
 <trip id="v-294" from="F0G0" to="A6A5" depart="294"/>
 <trip id="v-295" from="J7I7" to="C2B2" depart="295"/>
 <trip id="v-296" from="D3C3" to="F3F4" depart="296"/>
 <trip id="v-297" from="C5B5" to="B3B4" depart="297"/>
 <trip id="v-298" from="C0B0" to="G6H6" depart="298"/>
 <trip id="v-299" from="A9A8" to="C0B0" depart="299"/>
 <trip id="v-300" from="J7J8" to="J0I0" depart="300"/>
 <trip id="v-301" from="F4F3" to="G6H6" depart="301"/>
 <trip id="v-302" from="I1I0" to="D8D7" depart="302"/>
 <trip id="v-303" from="F9G9" to="D6E6" depart="303"/>
 <trip id="v-304" from="E5E6" to="G7G6" depart="304"/>
 <trip id="v-305" from="E7D7" to="H4G4" depart="305"/>
 <trip id="v-306" from="A8A7" to="H7I7" depart="306"/>
 <trip id="v-307" from="E6D6" to="J8J7" depart="307"/>
 <trip id="v-308" from="F4F3" to="J6J7" depart="308"/>
 <trip id="v-309" from="B0C0" to="C8D8" depart="309"/>
 <trip id="v-310" from="B0B1" to="I0I1" depart="310"/>
 <trip id="v-311" from="F2G2" to="C3C2" depart="311"/>
 <trip id="v-312" from="D9C9" to="E1E0" depart="312"/>
 <trip id="v-313" from="C1C0" to="D9D8" depart="313"/>
 <trip id="v-314" from="J7J6" to="D7D8" depart="314"/>
 <trip id="v-315" from="E6E7" to="H8H7" depart="315"/>
 <trip id="v-316" from="D0D1" to="F7F6" depart="316"/>
 <trip id="v-317" from="H9H8" to="C9C8" depart="317"/>
 <trip id="v-318" from="H1H0" to="D4C4" depart="318"/>
 <trip id="v-319" from="A3A2" to="J3I3" depart="319"/>
 <trip id="v-320" from="J9J8" to="I1J1" depart="320"/>
 <trip id="v-321" from="D2D3" to="G6F6" depart="321"/>
 <trip id="v-322" from="I3I4" to="I7J7" depart="322"/>
 <trip id="v-323" from="C5D5" to="G5F5" depart="323"/>
 <trip id="v-324" from="I5H5" to="D7D8" depart="324"/>
 <trip id="v-325" from="E7D7" to="G6H6" depart="325"/>
 <trip id="v-326" from="I0J0" to="A6A5" depart="326"/>
 <trip id="v-327" from="H1G1" to="J8J9" depart="327"/>
 <trip id="v-328" from="J4J3" to="G7H7" depart="328"/>
 <trip id="v-329" from="E8E9" to="F8F7" depart="329"/>
 <trip id="v-330" from="D0D1" to="H7I7" depart="330"/>
 <trip id="v-331" from="J1J0" to="G5F5" depart="331"/>
 <trip id="v-332" from="C8C9" to="F0G0" depart="332"/>
 <trip id="v-333" from="I4J4" to="H8H9" depart="333"/>
 <trip id="v-334" from="J2J3" to="H6I6" depart="334"/>
 <trip id="v-335" from="J6I6" to="A3A2" depart="335"/>
 <trip id="v-336" from="I7I8" to="I1J1" depart="336"/>
 <trip id="v-337" from="E4E3" to="F4G4" depart="337"/>
 <trip id="v-338" from="D7D6" to="J0I0" depart="338"/>
 <trip id="v-339" from="H5G5" to="B5A5" depart="339"/>
 <trip id="v-340" from="B4A4" to="E6D6" depart="340"/>
 <trip id="v-341" from="J3I3" to="I8J8" depart="341"/>
 <trip id="v-342" from="E2E3" to="C9B9" depart="342"/>
 <trip id="v-343" from="F6F5" to="H3G3" depart="343"/>
 <trip id="v-344" from="B2B3" to="J5I5" depart="344"/>
 <trip id="v-345" from="E0D0" to="F2G2" depart="345"/>
 <trip id="v-346" from="C2C3" to="G2F2" depart="346"/>
 <trip id="v-347" from="F5F6" to="F2F3" depart="347"/>
 <trip id="v-348" from="H0H1" to="B5C5" depart="348"/>
 <trip id="v-349" from="G5G6" to="C7B7" depart="349"/>
 <trip id="v-350" from="D5E5" to="F7F6" depart="350"/>
 <trip id="v-351" from="I3I2" to="C0C1" depart="351"/>
 <trip id="v-352" from="I2H2" to="F6F7" depart="352"/>
 <trip id="v-353" from="I7H7" to="J2J1" depart="353"/>
 <trip id="v-354" from="H8I8" to="F0F1" depart="354"/>
 <trip id="v-355" from="J6J5" to="H2H1" depart="355"/>
 <trip id="v-356" from="A4A3" to="C7D7" depart="356"/>
 <trip id="v-357" from="J3J4" to="D8E8" depart="357"/>
 <trip id="v-358" from="B1A1" to="H8H9" depart="358"/>
 <trip id="v-359" from="G8G7" to="B7B6" depart="359"/>
 <trip id="v-360" from="H8H9" to="C3D3" depart="360"/>
 <trip id="v-361" from="D3E3" to="H5I5" depart="361"/>
 <trip id="v-362" from="E0D0" to="A5B5" depart="362"/>
 <trip id="v-363" from="F2G2" to="E8D8" depart="363"/>
 <trip id="v-364" from="C0C1" to="G3G2" depart="364"/>
 <trip id="v-365" from="F2G2" to="B9A9" depart="365"/>
 <trip id="v-366" from="E0D0" to="I8I7" depart="366"/>
 <trip id="v-367" from="J0I0" to="D9C9" depart="367"/>
 <trip id="v-368" from="I0J0" to="E8D8" depart="368"/>
 <trip id="v-369" from="G8G9" to="I3I4" depart="369"/>
 <trip id="v-370" from="C7D7" to="J0I0" depart="370"/>
 <trip id="v-371" from="G6G7" to="C4D4" depart="371"/>
 <trip id="v-372" from="I9H9" to="D9D8" depart="372"/>
 <trip id="v-373" from="A0A1" to="G9H9" depart="373"/>
 <trip id="v-374" from="J7J8" to="H3G3" depart="374"/>
 <trip id="v-375" from="H5I5" to="C5D5" depart="375"/>
 <trip id="v-376" from="J7J6" to="B8C8" depart="376"/>
 <trip id="v-377" from="E3E4" to="D9E9" depart="377"/>
 <trip id="v-378" from="B0C0" to="G5G6" depart="378"/>
 <trip id="v-379" from="C3C4" to="G0H0" depart="379"/>
 <trip id="v-380" from="F6F5" to="D8D9" depart="380"/>
 <trip id="v-381" from="D2D3" to="E8D8" depart="381"/>
 <trip id="v-382" from="G0G1" to="B1A1" depart="382"/>
 <trip id="v-383" from="D5E5" to="C4B4" depart="383"/>
 <trip id="v-384" from="A4A3" to="I3H3" depart="384"/>
 <trip id="v-385" from="H0I0" to="E2D2" depart="385"/>
 <trip id="v-386" from="D1E1" to="A8A9" depart="386"/>
 <trip id="v-387" from="I4J4" to="I5H5" depart="387"/>
 <trip id="v-388" from="E2E3" to="I2H2" depart="388"/>
 <trip id="v-389" from="H2I2" to="E9D9" depart="389"/>
 <trip id="v-390" from="D7D6" to="F8F7" depart="390"/>
 <trip id="v-391" from="J8J7" to="B5B6" depart="391"/>
 <trip id="v-392" from="F1F2" to="G6G5" depart="392"/>
 <trip id="v-393" from="H5H6" to="F1F0" depart="393"/>
 <trip id="v-394" from="F4F3" to="H8I8" depart="394"/>
 <trip id="v-395" from="H6G6" to="F2G2" depart="395"/>
 <trip id="v-396" from="F2F3" to="F7G7" depart="396"/>
 <trip id="v-397" from="E3E4" to="H0I0" depart="397"/>
 <trip id="v-398" from="I2I1" to="I7I8" depart="398"/>
 <trip id="v-399" from="D2D1" to="I7J7" depart="399"/>
 <trip id="v-400" from="G3H3" to="B9C9" depart="400"/>
 <trip id="v-401" from="E0D0" to="J9J8" depart="401"/>
 <trip id="v-402" from="F5G5" to="D5E5" depart="402"/>
 <trip id="v-403" from="D6D5" to="G2H2" depart="403"/>
 <trip id="v-404" from="B3C3" to="H2G2" depart="404"/>
 <trip id="v-405" from="G2H2" to="B8A8" depart="405"/>
 <trip id="v-406" from="B4C4" to="F2F3" depart="406"/>
 <trip id="v-407" from="A5B5" to="G9H9" depart="407"/>
 <trip id="v-408" from="D4E4" to="J1J2" depart="408"/>
 <trip id="v-409" from="C2C3" to="H1H0" depart="409"/>
 <trip id="v-410" from="A0A1" to="I0H0" depart="410"/>
 <trip id="v-411" from="C9B9" to="I5H5" depart="411"/>
 <trip id="v-412" from="A6B6" to="J8J9" depart="412"/>
 <trip id="v-413" from="C6C5" to="B0A0" depart="413"/>
 <trip id="v-414" from="B3B2" to="E9D9" depart="414"/>
 <trip id="v-415" from="C5D5" to="D1C1" depart="415"/>
 <trip id="v-416" from="B7B8" to="F1F0" depart="416"/>
 <trip id="v-417" from="A7B7" to="E1E0" depart="417"/>
 <trip id="v-418" from="B1C1" to="F7F8" depart="418"/>
 <trip id="v-419" from="J1J2" to="D6D5" depart="419"/>
 <trip id="v-420" from="H4G4" to="J5J6" depart="420"/>
 <trip id="v-421" from="E7E6" to="F6G6" depart="421"/>
 <trip id="v-422" from="C4D4" to="H5G5" depart="422"/>
 <trip id="v-423" from="G2G1" to="B4B3" depart="423"/>
 <trip id="v-424" from="C1D1" to="H4G4" depart="424"/>
 <trip id="v-425" from="I5H5" to="J3J2" depart="425"/>
 <trip id="v-426" from="A0A1" to="D9D8" depart="426"/>
 <trip id="v-427" from="D2E2" to="H1G1" depart="427"/>
 <trip id="v-428" from="C8B8" to="E0E1" depart="428"/>
 <trip id="v-429" from="J4I4" to="H8I8" depart="429"/>
 <trip id="v-430" from="B8C8" to="E1D1" depart="430"/>
 <trip id="v-431" from="B7B8" to="J1I1" depart="431"/>
 <trip id="v-432" from="C6B6" to="A3A2" depart="432"/>
 <trip id="v-433" from="J8I8" to="D7D8" depart="433"/>
 <trip id="v-434" from="C4D4" to="E5E6" depart="434"/>
 <trip id="v-435" from="B3A3" to="J4I4" depart="435"/>
 <trip id="v-436" from="C9C8" to="B0C0" depart="436"/>
 <trip id="v-437" from="B3B4" to="I0J0" depart="437"/>
 <trip id="v-438" from="D0C0" to="A9B9" depart="438"/>
 <trip id="v-439" from="I7J7" to="C8B8" depart="439"/>
 <trip id="v-440" from="J2J3" to="E4E3" depart="440"/>
 <trip id="v-441" from="D9E9" to="B2B3" depart="441"/>
 <trip id="v-442" from="H8I8" to="D8D7" depart="442"/>
 <trip id="v-443" from="G5F5" to="H2I2" depart="443"/>
 <trip id="v-444" from="C3B3" to="G8G9" depart="444"/>
 <trip id="v-445" from="D5C5" to="G0H0" depart="445"/>
 <trip id="v-446" from="C4C3" to="J7I7" depart="446"/>
 <trip id="v-447" from="C9B9" to="A0B0" depart="447"/>
 <trip id="v-448" from="E5D5" to="F6G6" depart="448"/>
 <trip id="v-449" from="G3F3" to="F9G9" depart="449"/>
 <trip id="v-450" from="E6E7" to="D2D3" depart="450"/>
 <trip id="v-451" from="B4B3" to="B6C6" depart="451"/>
 <trip id="v-452" from="B6B7" to="B1C1" depart="452"/>
 <trip id="v-453" from="B0B1" to="F1F0" depart="453"/>
 <trip id="v-454" from="G1G2" to="B1B2" depart="454"/>
 <trip id="v-455" from="F8F9" to="A0B0" depart="455"/>
 <trip id="v-456" from="B2C2" to="H2I2" depart="456"/>
 <trip id="v-457" from="E3E2" to="B6B7" depart="457"/>
 <trip id="v-458" from="B1C1" to="J5J6" depart="458"/>
 <trip id="v-459" from="B8B7" to="B1C1" depart="459"/>
 <trip id="v-460" from="G8F8" to="H2G2" depart="460"/>
 <trip id="v-461" from="I4H4" to="C3C4" depart="461"/>
 <trip id="v-462" from="I2J2" to="I8I7" depart="462"/>
 <trip id="v-463" from="B3B4" to="F8G8" depart="463"/>
 <trip id="v-464" from="G7G6" to="E3E2" depart="464"/>
 <trip id="v-465" from="J3I3" to="C0C1" depart="465"/>
 <trip id="v-466" from="H2H1" to="A6B6" depart="466"/>
 <trip id="v-467" from="G8H8" to="F2F3" depart="467"/>
 <trip id="v-468" from="J5I5" to="D3D4" depart="468"/>
 <trip id="v-469" from="G8G9" to="D2D3" depart="469"/>
 <trip id="v-470" from="H6H5" to="E1E2" depart="470"/>
 <trip id="v-471" from="C4C3" to="J2I2" depart="471"/>
 <trip id="v-472" from="C4C3" to="I7H7" depart="472"/>
 <trip id="v-473" from="F8F7" to="D4D3" depart="473"/>
 <trip id="v-474" from="E0D0" to="I8J8" depart="474"/>
 <trip id="v-475" from="C3B3" to="E8E7" depart="475"/>
 <trip id="v-476" from="F4F3" to="A3A4" depart="476"/>
 <trip id="v-477" from="H8H9" to="A3B3" depart="477"/>
 <trip id="v-478" from="F2G2" to="E1E2" depart="478"/>
 <trip id="v-479" from="I7J7" to="G2G3" depart="479"/>
 <trip id="v-480" from="A0A1" to="B8B7" depart="480"/>
 <trip id="v-481" from="B3B2" to="A5B5" depart="481"/>
 <trip id="v-482" from="F8F7" to="A9B9" depart="482"/>
 <trip id="v-483" from="H7H6" to="H4I4" depart="483"/>
 <trip id="v-484" from="A4B4" to="D5C5" depart="484"/>
 <trip id="v-485" from="A6A7" to="G8G7" depart="485"/>
 <trip id="v-486" from="H6H5" to="B1C1" depart="486"/>
 <trip id="v-487" from="A8B8" to="E4E3" depart="487"/>
 <trip id="v-488" from="H5I5" to="A4B4" depart="488"/>
 <trip id="v-489" from="D8E8" to="F2G2" depart="489"/>
 <trip id="v-490" from="C9C8" to="E3D3" depart="490"/>
 <trip id="v-491" from="A7B7" to="F0G0" depart="491"/>
 <trip id="v-492" from="J6J7" to="A0A1" depart="492"/>
 <trip id="v-493" from="H2G2" to="B8B9" depart="493"/>
 <trip id="v-494" from="J0I0" to="C1D1" depart="494"/>
 <trip id="v-495" from="A9B9" to="J6J7" depart="495"/>
 <trip id="v-496" from="F9G9" to="B8A8" depart="496"/>
 <trip id="v-497" from="D9E9" to="D0E0" depart="497"/>
 <trip id="v-498" from="A2B2" to="D7E7" depart="498"/>
 <trip id="v-499" from="J3J2" to="B4C4" depart="499"/>
 <trip id="v-500" from="H6G6" to="E9D9" depart="500"/>
 <trip id="v-501" from="D2D3" to="I1H1" depart="501"/>
 <trip id="v-502" from="C8C9" to="F5F6" depart="502"/>
 <trip id="v-503" from="C6B6" to="J0I0" depart="503"/>
 <trip id="v-504" from="B5A5" to="B0C0" depart="504"/>
 <trip id="v-505" from="A7A6" to="I8J8" depart="505"/>
 <trip id="v-506" from="G0F0" to="C0C1" depart="506"/>
 <trip id="v-507" from="B0A0" to="G2G1" depart="507"/>
 <trip id="v-508" from="C1C2" to="J0J1" depart="508"/>
 <trip id="v-509" from="G4H4" to="C5C6" depart="509"/>
 <trip id="v-510" from="G4G3" to="B4C4" depart="510"/>
 <trip id="v-511" from="G0H0" to="G7F7" depart="511"/>
 <trip id="v-512" from="J5I5" to="D3E3" depart="512"/>
 <trip id="v-513" from="J9J8" to="B0C0" depart="513"/>
 <trip id="v-514" from="H4I4" to="E8D8" depart="514"/>
 <trip id="v-515" from="H9I9" to="D3D2" depart="515"/>
 <trip id="v-516" from="B6C6" to="H0G0" depart="516"/>
 <trip id="v-517" from="D8E8" to="F9F8" depart="517"/>
 <trip id="v-518" from="H9G9" to="B1A1" depart="518"/>
 <trip id="v-519" from="E1E0" to="H8H9" depart="519"/>
 <trip id="v-520" from="B0C0" to="J6J7" depart="520"/>
 <trip id="v-521" from="B5C5" to="A3B3" depart="521"/>
 <trip id="v-522" from="A9A8" to="H3H2" depart="522"/>
 <trip id="v-523" from="I5H5" to="F1G1" depart="523"/>
 <trip id="v-524" from="F0F1" to="A9A8" depart="524"/>
 <trip id="v-525" from="G8H8" to="I4J4" depart="525"/>
 <trip id="v-526" from="B8B9" to="I7J7" depart="526"/>
 <trip id="v-527" from="H2H1" to="F5G5" depart="527"/>
 <trip id="v-528" from="C1B1" to="C9D9" depart="528"/>
 <trip id="v-529" from="D0C0" to="G5G6" depart="529"/>
 <trip id="v-530" from="F4F3" to="A4B4" depart="530"/>
 <trip id="v-531" from="C0B0" to="H2I2" depart="531"/>
 <trip id="v-532" from="J8J9" to="A2B2" depart="532"/>
 <trip id="v-533" from="I9H9" to="E7D7" depart="533"/>
 <trip id="v-534" from="F5F6" to="H1I1" depart="534"/>
 <trip id="v-535" from="A1A0" to="F7G7" depart="535"/>
 <trip id="v-536" from="G3G2" to="E6E5" depart="536"/>
 <trip id="v-537" from="B7B6" to="D0C0" depart="537"/>
 <trip id="v-538" from="H7H6" to="D6E6" depart="538"/>
 <trip id="v-539" from="D1E1" to="A8A7" depart="539"/>
 <trip id="v-540" from="B0C0" to="F6G6" depart="540"/>
 <trip id="v-541" from="G5H5" to="G0G1" depart="541"/>
 <trip id="v-542" from="A2A1" to="G5H5" depart="542"/>
 <trip id="v-543" from="F5F6" to="C1D1" depart="543"/>
 <trip id="v-544" from="B9C9" to="J8J9" depart="544"/>
 <trip id="v-545" from="F4G4" to="A0B0" depart="545"/>
 <trip id="v-546" from="J2J1" to="H6H7" depart="546"/>
 <trip id="v-547" from="E4E3" to="H2H3" depart="547"/>
 <trip id="v-548" from="H4H3" to="B7B8" depart="548"/>
 <trip id="v-549" from="C6C7" to="D0E0" depart="549"/>
 <trip id="v-550" from="E6E5" to="B1A1" depart="550"/>
 <trip id="v-551" from="G3G2" to="B2B1" depart="551"/>
 <trip id="v-552" from="C7B7" to="E0D0" depart="552"/>
 <trip id="v-553" from="H1H0" to="E0E1" depart="553"/>
 <trip id="v-554" from="C7D7" to="E2E1" depart="554"/>
 <trip id="v-555" from="H6H7" to="A9B9" depart="555"/>
 <trip id="v-556" from="A2B2" to="F3F2" depart="556"/>
 <trip id="v-557" from="H9H8" to="E2E1" depart="557"/>
 <trip id="v-558" from="J4J3" to="H9I9" depart="558"/>
 <trip id="v-559" from="C2C3" to="I2H2" depart="559"/>
 <trip id="v-560" from="H2I2" to="G7G8" depart="560"/>
 <trip id="v-561" from="J9J8" to="G3G4" depart="561"/>
 <trip id="v-562" from="E8D8" to="F5F6" depart="562"/>
 <trip id="v-563" from="D1E1" to="G8G7" depart="563"/>
 <trip id="v-564" from="F6G6" to="C8D8" depart="564"/>
 <trip id="v-565" from="A2B2" to="B5A5" depart="565"/>
 <trip id="v-566" from="H3I3" to="A3A4" depart="566"/>
 <trip id="v-567" from="I9J9" to="B0A0" depart="567"/>
 <trip id="v-568" from="E7D7" to="F9F8" depart="568"/>
 <trip id="v-569" from="G1H1" to="B1B2" depart="569"/>
 <trip id="v-570" from="C6C5" to="A3A4" depart="570"/>
 <trip id="v-571" from="H0H1" to="H6I6" depart="571"/>
 <trip id="v-572" from="C6C7" to="I2I3" depart="572"/>
 <trip id="v-573" from="C2C3" to="H3I3" depart="573"/>
 <trip id="v-574" from="C5B5" to="E3E4" depart="574"/>
 <trip id="v-575" from="J8J7" to="E4E3" depart="575"/>
 <trip id="v-576" from="G1G0" to="H6H5" depart="576"/>
 <trip id="v-577" from="B7C7" to="C3D3" depart="577"/>
 <trip id="v-578" from="F4F3" to="H6H5" depart="578"/>
 <trip id="v-579" from="I4J4" to="F7F6" depart="579"/>
 <trip id="v-580" from="G0H0" to="C4B4" depart="580"/>
 <trip id="v-581" from="J0J1" to="C5D5" depart="581"/>
 <trip id="v-582" from="D3D2" to="D8C8" depart="582"/>
 <trip id="v-583" from="G9H9" to="B0B1" depart="583"/>
 <trip id="v-584" from="E0E1" to="I2I3" depart="584"/>
 <trip id="v-585" from="C1D1" to="B7B8" depart="585"/>
 <trip id="v-586" from="F1F0" to="C7D7" depart="586"/>
 <trip id="v-587" from="D7C7" to="F2G2" depart="587"/>
 <trip id="v-588" from="G6G7" to="H0I0" depart="588"/>
 <trip id="v-589" from="G1H1" to="J6J5" depart="589"/>
 <trip id="v-590" from="E2D2" to="J4I4" depart="590"/>
 <trip id="v-591" from="I4H4" to="D4C4" depart="591"/>
 <trip id="v-592" from="D3E3" to="F1F0" depart="592"/>
 <trip id="v-593" from="H7H6" to="D8E8" depart="593"/>
 <trip id="v-594" from="A3B3" to="G9H9" depart="594"/>
 <trip id="v-595" from="H3H4" to="C8D8" depart="595"/>
 <trip id="v-596" from="B0B1" to="I6I5" depart="596"/>
 <trip id="v-597" from="D0C0" to="F6G6" depart="597"/>
 <trip id="v-598" from="G0H0" to="I9I8" depart="598"/>
 <trip id="v-599" from="B9C9" to="E1D1" depart="599"/>
 <trip id="v-600" from="F1F0" to="E1E2" depart="600"/>
 <trip id="v-601" from="F2G2" to="G8G9" depart="601"/>
 <trip id="v-602" from="A8A9" to="G4G3" depart="602"/>
 <trip id="v-603" from="I6I7" to="F2F3" depart="603"/>
 <trip id="v-604" from="B5B6" to="I0H0" depart="604"/>
 <trip id="v-605" from="D2C2" to="B7B8" depart="605"/>
 <trip id="v-606" from="D9D8" to="G3H3" depart="606"/>
 <trip id="v-607" from="A8A7" to="D4D3" depart="607"/>
 <trip id="v-608" from="D7D8" to="I6H6" depart="608"/>
 <trip id="v-609" from="B3C3" to="J5I5" depart="609"/>
 <trip id="v-610" from="D7C7" to="A2B2" depart="610"/>
 <trip id="v-611" from="B8C8" to="J4J3" depart="611"/>
 <trip id="v-612" from="G0F0" to="I8H8" depart="612"/>
 <trip id="v-613" from="A5A6" to="F0G0" depart="613"/>
 <trip id="v-614" from="C8B8" to="I9I8" depart="614"/>
 <trip id="v-615" from="G3H3" to="J9J8" depart="615"/>
 <trip id="v-616" from="I5I6" to="D3E3" depart="616"/>
 <trip id="v-617" from="G8G7" to="D6D7" depart="617"/>
 <trip id="v-618" from="C3D3" to="F0G0" depart="618"/>
 <trip id="v-619" from="I3I2" to="F7F6" depart="619"/>
 <trip id="v-620" from="A1A2" to="H9G9" depart="620"/>
 <trip id="v-621" from="B1B0" to="G0H0" depart="621"/>
 <trip id="v-622" from="D5C5" to="F1G1" depart="622"/>
 <trip id="v-623" from="J5J6" to="C8C7" depart="623"/>
 <trip id="v-624" from="F5F6" to="B3B4" depart="624"/>
 <trip id="v-625" from="B6C6" to="E4E3" depart="625"/>
 <trip id="v-626" from="F9F8" to="C8B8" depart="626"/>
 <trip id="v-627" from="H8I8" to="E2D2" depart="627"/>
 <trip id="v-628" from="D6D7" to="E2D2" depart="628"/>
 <trip id="v-629" from="B0B1" to="I0H0" depart="629"/>
 <trip id="v-630" from="J0J1" to="F5F6" depart="630"/>
 <trip id="v-631" from="D4D3" to="F3G3" depart="631"/>
 <trip id="v-632" from="D3C3" to="H3H2" depart="632"/>
 <trip id="v-633" from="J4I4" to="C4B4" depart="633"/>
 <trip id="v-634" from="F6F7" to="C3B3" depart="634"/>
 <trip id="v-635" from="G8F8" to="D0C0" depart="635"/>
 <trip id="v-636" from="I6H6" to="I0I1" depart="636"/>
 <trip id="v-637" from="J8J7" to="J4J3" depart="637"/>
 <trip id="v-638" from="G0H0" to="B7B6" depart="638"/>
 <trip id="v-639" from="E7E8" to="J8J7" depart="639"/>
 <trip id="v-640" from="E9D9" to="J9J8" depart="640"/>
 <trip id="v-641" from="F2F1" to="G6F6" depart="641"/>
 <trip id="v-642" from="G2F2" to="E3E2" depart="642"/>
 <trip id="v-643" from="E2E3" to="C8B8" depart="643"/>
 <trip id="v-644" from="J3J4" to="C0D0" depart="644"/>
 <trip id="v-645" from="A3A2" to="F0G0" depart="645"/>
 <trip id="v-646" from="J7I7" to="I1I0" depart="646"/>
 <trip id="v-647" from="G9F9" to="E7D7" depart="647"/>
 <trip id="v-648" from="F1G1" to="G6G7" depart="648"/>
 <trip id="v-649" from="F4G4" to="I5H5" depart="649"/>
 <trip id="v-650" from="D7C7" to="G3F3" depart="650"/>
 <trip id="v-651" from="E8E7" to="C1D1" depart="651"/>
 <trip id="v-652" from="E1E2" to="J3J2" depart="652"/>
 <trip id="v-653" from="A3A4" to="F9G9" depart="653"/>
 <trip id="v-654" from="B9A9" to="H0H1" depart="654"/>
 <trip id="v-655" from="G9F9" to="A4B4" depart="655"/>
 <trip id="v-656" from="F0F1" to="D8D9" depart="656"/>
 <trip id="v-657" from="H3G3" to="I8J8" depart="657"/>
 <trip id="v-658" from="J9J8" to="E5E6" depart="658"/>
 <trip id="v-659" from="G3G4" to="J6J5" depart="659"/>
 <trip id="v-660" from="D9D8" to="H5I5" depart="660"/>
 <trip id="v-661" from="E8D8" to="H2I2" depart="661"/>
 <trip id="v-662" from="C9B9" to="A1A2" depart="662"/>
 <trip id="v-663" from="I2I3" to="G9H9" depart="663"/>
 <trip id="v-664" from="C6B6" to="F6F7" depart="664"/>
 <trip id="v-665" from="D9E9" to="G4G3" depart="665"/>
 <trip id="v-666" from="D2C2" to="A7B7" depart="666"/>
 <trip id="v-667" from="H3H2" to="A0A1" depart="667"/>
 <trip id="v-668" from="H8G8" to="H4G4" depart="668"/>
 <trip id="v-669" from="D4E4" to="A6A7" depart="669"/>
 <trip id="v-670" from="A7A6" to="G2H2" depart="670"/>
 <trip id="v-671" from="A3B3" to="F7G7" depart="671"/>
 <trip id="v-672" from="I8I7" to="C8B8" depart="672"/>
 <trip id="v-673" from="J5I5" to="B6A6" depart="673"/>
 <trip id="v-674" from="F4F3" to="F8F7" depart="674"/>
 <trip id="v-675" from="A7A8" to="G0H0" depart="675"/>
 <trip id="v-676" from="D2D1" to="D7C7" depart="676"/>
 <trip id="v-677" from="H0I0" to="C6C5" depart="677"/>
 <trip id="v-678" from="I6H6" to="H3I3" depart="678"/>
 <trip id="v-679" from="C5B5" to="E0D0" depart="679"/>
 <trip id="v-680" from="I2I1" to="E3E2" depart="680"/>
 <trip id="v-681" from="I7H7" to="G0F0" depart="681"/>
 <trip id="v-682" from="F0G0" to="D7D8" depart="682"/>
 <trip id="v-683" from="G4G3" to="I7I6" depart="683"/>
 <trip id="v-684" from="E1D1" to="G1G0" depart="684"/>
 <trip id="v-685" from="A4A3" to="I5J5" depart="685"/>
 <trip id="v-686" from="D1C1" to="E8E9" depart="686"/>
 <trip id="v-687" from="B5C5" to="G4G3" depart="687"/>
 <trip id="v-688" from="D7E7" to="J1J2" depart="688"/>
 <trip id="v-689" from="H3H2" to="F5F6" depart="689"/>
 <trip id="v-690" from="E9E8" to="D3D4" depart="690"/>
 <trip id="v-691" from="J9I9" to="D2C2" depart="691"/>
 <trip id="v-692" from="A4A3" to="J9J8" depart="692"/>
 <trip id="v-693" from="G4F4" to="A8A7" depart="693"/>
 <trip id="v-694" from="I6I7" to="H3I3" depart="694"/>
 <trip id="v-695" from="C8C7" to="D2E2" depart="695"/>
 <trip id="v-696" from="F6F7" to="D2C2" depart="696"/>
 <trip id="v-697" from="A1B1" to="H4G4" depart="697"/>
 <trip id="v-698" from="F7F8" to="A1A2" depart="698"/>
 <trip id="v-699" from="J2J3" to="A8B8" depart="699"/>
 <trip id="v-700" from="J6J5" to="A8A7" depart="700"/>
 <trip id="v-701" from="A9B9" to="B1B2" depart="701"/>
 <trip id="v-702" from="I9H9" to="B9B8" depart="702"/>
 <trip id="v-703" from="F0G0" to="B1B0" depart="703"/>
 <trip id="v-704" from="J3J4" to="E0E1" depart="704"/>
 <trip id="v-705" from="H5H6" to="B5A5" depart="705"/>
 <trip id="v-706" from="C2C1" to="J0J1" depart="706"/>
 <trip id="v-707" from="J9I9" to="B0B1" depart="707"/>
 <trip id="v-708" from="C3C2" to="J0I0" depart="708"/>
 <trip id="v-709" from="A8A7" to="I0H0" depart="709"/>
 <trip id="v-710" from="G8G9" to="A8A9" depart="710"/>
 <trip id="v-711" from="B8C8" to="F7G7" depart="711"/>
 <trip id="v-712" from="B2B3" to="H2H1" depart="712"/>
 <trip id="v-713" from="A0A1" to="F1G1" depart="713"/>
 <trip id="v-714" from="F3F2" to="E3E2" depart="714"/>
 <trip id="v-715" from="B9A9" to="I5I6" depart="715"/>
 <trip id="v-716" from="A1B1" to="J5I5" depart="716"/>
 <trip id="v-717" from="H1I1" to="D5C5" depart="717"/>
 <trip id="v-718" from="B7B6" to="F7F6" depart="718"/>
 <trip id="v-719" from="H3G3" to="B0B1" depart="719"/>
 <trip id="v-720" from="E7D7" to="J1I1" depart="720"/>
 <trip id="v-721" from="D6E6" to="F2F3" depart="721"/>
 <trip id="v-722" from="D2E2" to="C8B8" depart="722"/>
 <trip id="v-723" from="H1H0" to="I7J7" depart="723"/>
 <trip id="v-724" from="F2F1" to="F7F8" depart="724"/>
 <trip id="v-725" from="H4H3" to="C6C5" depart="725"/>
 <trip id="v-726" from="G8F8" to="A1A2" depart="726"/>
 <trip id="v-727" from="A6A7" to="F6G6" depart="727"/>
 <trip id="v-728" from="I9I8" to="B7A7" depart="728"/>
 <trip id="v-729" from="I1I0" to="A8B8" depart="729"/>
 <trip id="v-730" from="I2J2" to="B2B3" depart="730"/>
 <trip id="v-731" from="H8I8" to="C0D0" depart="731"/>
 <trip id="v-732" from="A9A8" to="B2A2" depart="732"/>
 <trip id="v-733" from="H5I5" to="F0F1" depart="733"/>
 <trip id="v-734" from="A6B6" to="C3D3" depart="734"/>
 <trip id="v-735" from="E1E0" to="G7F7" depart="735"/>
 <trip id="v-736" from="F5F6" to="D4C4" depart="736"/>
 <trip id="v-737" from="E6E7" to="I7I8" depart="737"/>
 <trip id="v-738" from="F1G1" to="A2A1" depart="738"/>
 <trip id="v-739" from="H3I3" to="A5B5" depart="739"/>
 <trip id="v-740" from="D5E5" to="E2D2" depart="740"/>
 <trip id="v-741" from="A8B8" to="I8H8" depart="741"/>
 <trip id="v-742" from="B8B9" to="H9G9" depart="742"/>
 <trip id="v-743" from="J4J3" to="B0A0" depart="743"/>
 <trip id="v-744" from="A8B8" to="F7F6" depart="744"/>
 <trip id="v-745" from="A5A6" to="I5J5" depart="745"/>
 <trip id="v-746" from="C7D7" to="H2H1" depart="746"/>
 <trip id="v-747" from="A2B2" to="A7A6" depart="747"/>
 <trip id="v-748" from="D8C8" to="F5G5" depart="748"/>
 <trip id="v-749" from="H5I5" to="E4E3" depart="749"/>
 <trip id="v-750" from="G0G1" to="F8F9" depart="750"/>
 <trip id="v-751" from="F3F4" to="C6B6" depart="751"/>
 <trip id="v-752" from="E0D0" to="J8J7" depart="752"/>
 <trip id="v-753" from="E3E2" to="F6F5" depart="753"/>
 <trip id="v-754" from="A8A9" to="F6F7" depart="754"/>
 <trip id="v-755" from="A3A4" to="H0H1" depart="755"/>
 <trip id="v-756" from="C2B2" to="I1I2" depart="756"/>
 <trip id="v-757" from="B1A1" to="C8D8" depart="757"/>
 <trip id="v-758" from="F7G7" to="C2D2" depart="758"/>
 <trip id="v-759" from="B6C6" to="J3J4" depart="759"/>
 <trip id="v-760" from="D0C0" to="D7D6" depart="760"/>
 <trip id="v-761" from="B4B3" to="G9F9" depart="761"/>
 <trip id="v-762" from="E8E9" to="A1B1" depart="762"/>
 <trip id="v-763" from="J9J8" to="B4A4" depart="763"/>
 <trip id="v-764" from="D2C2" to="G0G1" depart="764"/>
 <trip id="v-765" from="E0D0" to="I9J9" depart="765"/>
 <trip id="v-766" from="I1J1" to="C9C8" depart="766"/>
 <trip id="v-767" from="A3A4" to="J4J3" depart="767"/>
 <trip id="v-768" from="E8D8" to="I4H4" depart="768"/>
 <trip id="v-769" from="J4J3" to="B0C0" depart="769"/>
 <trip id="v-770" from="I0I1" to="F7F8" depart="770"/>
 <trip id="v-771" from="J5I5" to="B4C4" depart="771"/>
 <trip id="v-772" from="E5E6" to="C1D1" depart="772"/>
 <trip id="v-773" from="G9G8" to="B7B8" depart="773"/>
 <trip id="v-774" from="F0F1" to="C2C1" depart="774"/>
 <trip id="v-775" from="I5J5" to="G0F0" depart="775"/>
 <trip id="v-776" from="D9E9" to="J9J8" depart="776"/>
 <trip id="v-777" from="E9D9" to="F5G5" depart="777"/>
 <trip id="v-778" from="J0I0" to="I5I6" depart="778"/>
 <trip id="v-779" from="I7J7" to="F3F4" depart="779"/>
 <trip id="v-780" from="F0G0" to="H5H6" depart="780"/>
 <trip id="v-781" from="C5B5" to="F6F7" depart="781"/>
 <trip id="v-782" from="E0E1" to="B5C5" depart="782"/>
 <trip id="v-783" from="I6I7" to="E5D5" depart="783"/>
 <trip id="v-784" from="C6D6" to="G0F0" depart="784"/>
 <trip id="v-785" from="H4G4" to="B2B3" depart="785"/>
 <trip id="v-786" from="A4A3" to="H1H0" depart="786"/>
 <trip id="v-787" from="C3C2" to="H4I4" depart="787"/>
 <trip id="v-788" from="B4C4" to="I4I3" depart="788"/>
 <trip id="v-789" from="I9J9" to="A5A6" depart="789"/>
 <trip id="v-790" from="B1A1" to="H3I3" depart="790"/>
 <trip id="v-791" from="H3I3" to="B3B2" depart="791"/>
 <trip id="v-792" from="B6A6" to="F5F6" depart="792"/>
 <trip id="v-793" from="J3J4" to="D6C6" depart="793"/>
 <trip id="v-794" from="F3F2" to="B2B1" depart="794"/>
 <trip id="v-795" from="D2E2" to="F5G5" depart="795"/>
 <trip id="v-796" from="D7D8" to="H9I9" depart="796"/>
 <trip id="v-797" from="I9I8" to="C9C8" depart="797"/>
 <trip id="v-798" from="H7G7" to="I4J4" depart="798"/>
 <trip id="v-799" from="J1J2" to="E4E3" depart="799"/>
 <trip id="v-800" from="A5A6" to="G1G2" depart="800"/>
 <trip id="v-801" from="C3B3" to="E6D6" depart="801"/>
 <trip id="v-802" from="H9G9" to="C6C7" depart="802"/>
 <trip id="v-803" from="D3E3" to="H5H6" depart="803"/>
 <trip id="v-804" from="E5E6" to="B3C3" depart="804"/>
 <trip id="v-805" from="D1D0" to="D5D6" depart="805"/>
 <trip id="v-806" from="G5G6" to="E6D6" depart="806"/>
 <trip id="v-807" from="D5E5" to="J8I8" depart="807"/>
 <trip id="v-808" from="B8B7" to="I2I3" depart="808"/>
 <trip id="v-809" from="E4E3" to="I7I8" depart="809"/>
 <trip id="v-810" from="E3D3" to="F0F1" depart="810"/>
 <trip id="v-811" from="C9B9" to="J9J8" depart="811"/>
 <trip id="v-812" from="H1H2" to="A2A1" depart="812"/>
 <trip id="v-813" from="E4D4" to="I6H6" depart="813"/>
 <trip id="v-814" from="I5J5" to="D9E9" depart="814"/>
 <trip id="v-815" from="E9D9" to="B1B2" depart="815"/>
 <trip id="v-816" from="E6E5" to="I0I1" depart="816"/>
 <trip id="v-817" from="E4E3" to="E5D5" depart="817"/>
 <trip id="v-818" from="A4B4" to="J7J6" depart="818"/>
 <trip id="v-819" from="B0B1" to="F1G1" depart="819"/>
 <trip id="v-820" from="B6A6" to="G0F0" depart="820"/>
 <trip id="v-821" from="F4F3" to="G8G7" depart="821"/>
 <trip id="v-822" from="E4E3" to="J0J1" depart="822"/>
 <trip id="v-823" from="I8I7" to="F2F1" depart="823"/>
 <trip id="v-824" from="B6C6" to="B4A4" depart="824"/>
 <trip id="v-825" from="C3C4" to="D6D5" depart="825"/>
 <trip id="v-826" from="E6E5" to="E1E2" depart="826"/>
 <trip id="v-827" from="A5A6" to="D3E3" depart="827"/>
 <trip id="v-828" from="J0I0" to="D3E3" depart="828"/>
 <trip id="v-829" from="H5H6" to="H4G4" depart="829"/>
 <trip id="v-830" from="H6H5" to="A1A0" depart="830"/>
 <trip id="v-831" from="D2D1" to="F6F5" depart="831"/>
 <trip id="v-832" from="H7I7" to="E3E4" depart="832"/>
 <trip id="v-833" from="H1G1" to="B3A3" depart="833"/>
 <trip id="v-834" from="A3B3" to="G8H8" depart="834"/>
 <trip id="v-835" from="I4J4" to="H9I9" depart="835"/>
 <trip id="v-836" from="I6J6" to="G3G2" depart="836"/>
 <trip id="v-837" from="F4F3" to="H8G8" depart="837"/>
 <trip id="v-838" from="D0C0" to="G9G8" depart="838"/>
 <trip id="v-839" from="C5C6" to="J5J6" depart="839"/>
 <trip id="v-840" from="H3H4" to="J6J7" depart="840"/>
 <trip id="v-841" from="C6C5" to="H2I2" depart="841"/>
 <trip id="v-842" from="E7D7" to="I2I3" depart="842"/>
 <trip id="v-843" from="B4C4" to="E7D7" depart="843"/>
 <trip id="v-844" from="G9G8" to="B4A4" depart="844"/>
 <trip id="v-845" from="E3E4" to="J4I4" depart="845"/>
 <trip id="v-846" from="D6D5" to="H7H6" depart="846"/>
 <trip id="v-847" from="B1C1" to="G0G1" depart="847"/>
 <trip id="v-848" from="A2A1" to="H1I1" depart="848"/>
 <trip id="v-849" from="D7E7" to="B0A0" depart="849"/>
 <trip id="v-850" from="D7D6" to="H8G8" depart="850"/>
 <trip id="v-851" from="E7D7" to="G9H9" depart="851"/>
 <trip id="v-852" from="C5C6" to="H1H2" depart="852"/>
 <trip id="v-853" from="B1A1" to="J4J3" depart="853"/>
 <trip id="v-854" from="I5J5" to="C6C5" depart="854"/>
 <trip id="v-855" from="E5E6" to="H3G3" depart="855"/>
 <trip id="v-856" from="E2D2" to="G2F2" depart="856"/>
 <trip id="v-857" from="D9C9" to="G7G8" depart="857"/>
 <trip id="v-858" from="H3I3" to="D2C2" depart="858"/>
 <trip id="v-859" from="H0H1" to="G9F9" depart="859"/>
 <trip id="v-860" from="I4H4" to="F9F8" depart="860"/>
 <trip id="v-861" from="I6H6" to="D2C2" depart="861"/>
 <trip id="v-862" from="A7A8" to="A4A3" depart="862"/>
 <trip id="v-863" from="G6G5" to="J1I1" depart="863"/>
 <trip id="v-864" from="I7H7" to="C2C1" depart="864"/>
 <trip id="v-865" from="E3D3" to="F1F2" depart="865"/>
 <trip id="v-866" from="G3H3" to="I6H6" depart="866"/>
 <trip id="v-867" from="E8E7" to="F6G6" depart="867"/>
 <trip id="v-868" from="J2J3" to="E8E7" depart="868"/>
 <trip id="v-869" from="C3B3" to="C6C5" depart="869"/>
 <trip id="v-870" from="F8F7" to="I4J4" depart="870"/>
 <trip id="v-871" from="F2F1" to="D2D1" depart="871"/>
 <trip id="v-872" from="I9J9" to="J2I2" depart="872"/>
 <trip id="v-873" from="C3D3" to="E8E9" depart="873"/>
 <trip id="v-874" from="H1G1" to="H7H6" depart="874"/>
 <trip id="v-875" from="C6C7" to="B1B0" depart="875"/>
 <trip id="v-876" from="B8B9" to="B1C1" depart="876"/>
 <trip id="v-877" from="A4A3" to="F2G2" depart="877"/>
 <trip id="v-878" from="G3G4" to="G9H9" depart="878"/>
 <trip id="v-879" from="J3I3" to="C0D0" depart="879"/>
 <trip id="v-880" from="D4E4" to="F4G4" depart="880"/>
 <trip id="v-881" from="I5J5" to="A3A2" depart="881"/>
 <trip id="v-882" from="A6A7" to="D2D3" depart="882"/>
 <trip id="v-883" from="A9B9" to="I2H2" depart="883"/>
 <trip id="v-884" from="F1F2" to="A3A4" depart="884"/>
 <trip id="v-885" from="F2G2" to="F6G6" depart="885"/>
 <trip id="v-886" from="B9C9" to="F1G1" depart="886"/>
 <trip id="v-887" from="B8B7" to="I7I6" depart="887"/>
 <trip id="v-888" from="F7F6" to="J3I3" depart="888"/>
 <trip id="v-889" from="G1G0" to="C3B3" depart="889"/>
 <trip id="v-890" from="I2I1" to="J5J6" depart="890"/>
 <trip id="v-891" from="G6F6" to="E9E8" depart="891"/>
 <trip id="v-892" from="A8B8" to="H6I6" depart="892"/>
 <trip id="v-893" from="F9F8" to="B0B1" depart="893"/>
 <trip id="v-894" from="E8E9" to="E4E3" depart="894"/>
 <trip id="v-895" from="F7F8" to="E4E3" depart="895"/>
 <trip id="v-896" from="F7G7" to="H3H2" depart="896"/>
 <trip id="v-897" from="C3B3" to="G5H5" depart="897"/>
 <trip id="v-898" from="D9D8" to="J0I0" depart="898"/>
 <trip id="v-899" from="G3G2" to="G7G6" depart="899"/>
 <trip id="v-900" from="F6F5" to="H4I4" depart="900"/>
 <trip id="v-901" from="H2H3" to="F8F7" depart="901"/>
 <trip id="v-902" from="J5J6" to="E7E8" depart="902"/>
 <trip id="v-903" from="B7B6" to="I9J9" depart="903"/>
 <trip id="v-904" from="J2J3" to="A3A2" depart="904"/>
 <trip id="v-905" from="I6H6" to="E0D0" depart="905"/>
 <trip id="v-906" from="A2A1" to="H2I2" depart="906"/>
 <trip id="v-907" from="C2C3" to="J4J3" depart="907"/>
 <trip id="v-908" from="B0A0" to="J2I2" depart="908"/>
 <trip id="v-909" from="I0H0" to="C1B1" depart="909"/>
 <trip id="v-910" from="H3I3" to="E0D0" depart="910"/>
 <trip id="v-911" from="G2H2" to="C3B3" depart="911"/>
 <trip id="v-912" from="C8D8" to="D1C1" depart="912"/>
 <trip id="v-913" from="A1B1" to="J5I5" depart="913"/>
 <trip id="v-914" from="B1C1" to="G1F1" depart="914"/>
 <trip id="v-915" from="E4D4" to="I0J0" depart="915"/>
 <trip id="v-916" from="H5H6" to="D5C5" depart="916"/>
 <trip id="v-917" from="I7I8" to="B9B8" depart="917"/>
 <trip id="v-918" from="I0J0" to="I6J6" depart="918"/>
 <trip id="v-919" from="F1F2" to="E8E7" depart="919"/>
 <trip id="v-920" from="I5J5" to="D2E2" depart="920"/>
 <trip id="v-921" from="I4J4" to="B5A5" depart="921"/>
 <trip id="v-922" from="H2G2" to="I6I5" depart="922"/>
 <trip id="v-923" from="B3B2" to="J4I4" depart="923"/>
 <trip id="v-924" from="B4A4" to="I5H5" depart="924"/>
 <trip id="v-925" from="A6A5" to="G3H3" depart="925"/>
 <trip id="v-926" from="B8C8" to="F9F8" depart="926"/>
 <trip id="v-927" from="E9D9" to="B0A0" depart="927"/>
 <trip id="v-928" from="H5G5" to="D2D3" depart="928"/>
 <trip id="v-929" from="D9C9" to="I7H7" depart="929"/>
 <trip id="v-930" from="J7J8" to="D2D3" depart="930"/>
 <trip id="v-931" from="I6J6" to="F1F0" depart="931"/>
 <trip id="v-932" from="G1G2" to="F7F8" depart="932"/>
 <trip id="v-933" from="H5G5" to="B3B2" depart="933"/>
 <trip id="v-934" from="A8B8" to="F0G0" depart="934"/>
 <trip id="v-935" from="C1B1" to="F9F8" depart="935"/>
 <trip id="v-936" from="B6C6" to="G0G1" depart="936"/>
 <trip id="v-937" from="A2A3" to="A9B9" depart="937"/>
 <trip id="v-938" from="C4B4" to="J4J3" depart="938"/>
 <trip id="v-939" from="D2E2" to="H6H5" depart="939"/>
 <trip id="v-940" from="J2J1" to="C4C3" depart="940"/>
 <trip id="v-941" from="J0J1" to="G6G5" depart="941"/>
 <trip id="v-942" from="H5G5" to="H1H0" depart="942"/>
 <trip id="v-943" from="B3B4" to="D9D8" depart="943"/>
 <trip id="v-944" from="C0D0" to="H9G9" depart="944"/>
 <trip id="v-945" from="D0D1" to="I1I0" depart="945"/>
 <trip id="v-946" from="J7I7" to="C8B8" depart="946"/>
 <trip id="v-947" from="D4E4" to="C5D5" depart="947"/>
 <trip id="v-948" from="I0I1" to="A8B8" depart="948"/>
 <trip id="v-949" from="J8J9" to="C8B8" depart="949"/>
 <trip id="v-950" from="E7E8" to="C1D1" depart="950"/>
 <trip id="v-951" from="D0C0" to="H0H1" depart="951"/>
 <trip id="v-952" from="H6G6" to="I4J4" depart="952"/>
 <trip id="v-953" from="E3E2" to="F5G5" depart="953"/>
 <trip id="v-954" from="C9C8" to="E0D0" depart="954"/>
 <trip id="v-955" from="G0G1" to="F6F5" depart="955"/>
 <trip id="v-956" from="E5D5" to="F3F4" depart="956"/>
 <trip id="v-957" from="B2A2" to="B6B5" depart="957"/>
 <trip id="v-958" from="C7C6" to="I4H4" depart="958"/>
 <trip id="v-959" from="E8D8" to="A0A1" depart="959"/>
 <trip id="v-960" from="A2A1" to="E5E6" depart="960"/>
 <trip id="v-961" from="J8J9" to="E1E0" depart="961"/>
 <trip id="v-962" from="I8I7" to="F1F0" depart="962"/>
 <trip id="v-963" from="B9C9" to="J4J3" depart="963"/>
 <trip id="v-964" from="A3A4" to="J3J4" depart="964"/>
 <trip id="v-965" from="H7H6" to="F0F1" depart="965"/>
 <trip id="v-966" from="I2H2" to="H5H6" depart="966"/>
 <trip id="v-967" from="I3J3" to="A5B5" depart="967"/>
 <trip id="v-968" from="B2A2" to="B7B8" depart="968"/>
 <trip id="v-969" from="G5H5" to="B3B2" depart="969"/>
 <trip id="v-970" from="G4G3" to="D2E2" depart="970"/>
 <trip id="v-971" from="J0J1" to="F8G8" depart="971"/>
 <trip id="v-972" from="G8F8" to="G0H0" depart="972"/>
 <trip id="v-973" from="B4C4" to="F7F6" depart="973"/>
 <trip id="v-974" from="I0I1" to="I8I9" depart="974"/>
 <trip id="v-975" from="F0G0" to="E7E8" depart="975"/>
 <trip id="v-976" from="F6G6" to="D8C8" depart="976"/>
 <trip id="v-977" from="H0H1" to="A5A6" depart="977"/>
 <trip id="v-978" from="D5D6" to="J4J3" depart="978"/>
 <trip id="v-979" from="I1I2" to="A6A7" depart="979"/>
 <trip id="v-980" from="I8I7" to="F1F0" depart="980"/>
 <trip id="v-981" from="G8H8" to="B9A9" depart="981"/>
 <trip id="v-982" from="A0A1" to="D7C7" depart="982"/>
 <trip id="v-983" from="D0D1" to="G7H7" depart="983"/>
 <trip id="v-984" from="D9E9" to="A2B2" depart="984"/>
 <trip id="v-985" from="C6D6" to="H5H6" depart="985"/>
 <trip id="v-986" from="C2D2" to="G0H0" depart="986"/>
 <trip id="v-987" from="G8G7" to="F1F0" depart="987"/>
 <trip id="v-988" from="I6H6" to="B3B2" depart="988"/>
 <trip id="v-989" from="F1G1" to="C8D8" depart="989"/>
 <trip id="v-990" from="J4J3" to="B6B5" depart="990"/>
 <trip id="v-991" from="I3I2" to="H8H7" depart="991"/>
 <trip id="v-992" from="H9I9" to="A1A0" depart="992"/>
 <trip id="v-993" from="B4C4" to="H1H0" depart="993"/>
 <trip id="v-994" from="C7B7" to="I5J5" depart="994"/>
 <trip id="v-995" from="D3D4" to="E5D5" depart="995"/>
 <trip id="v-996" from="E7E8" to="F5F6" depart="996"/>
 <trip id="v-997" from="C8D8" to="F7F8" depart="997"/>
 <trip id="v-998" from="E0E1" to="C6D6" depart="998"/>
 <trip id="v-999" from="I3I2" to="A5A6" depart="999"/>
</routes>
